aquasec/__init__.py
aquasec/_version.py
aquasec/api.py
aquasec/auth.py
aquasec/configs.py
aquasec/delete.py
aquasec/exceptions.py
aquasec/get.py
aquasec/logging.py
aquasec/post.py
aquasec/put.py
aquasec/requestapi.py
aquasec/statics.py
aquasec/structures.py
aquasec/utilities.py
aquasec/orchestration/__init__.py
aquasec/orchestration/bench_report.py
aquasec_api-0.0.4.dist-info/LICENSE
aquasec_api-0.0.4.dist-info/METADATA
aquasec_api-0.0.4.dist-info/WHEEL
aquasec_api-0.0.4.dist-info/top_level.txt
aquasec_api-0.0.4.dist-info/zip-safe
aquasec_api-0.0.4.dist-info/RECORD
