Metadata-Version: 2.1
Name: aquasec-api
Version: 0.0.4
Summary: Aqua Security SDK to pull data from Aquasec Tenant and CSPM for auditing
Author: atav928
Author-email: atav928 <dev@tavnets.com>
License: GNU GENERAL PUBLIC LICENSE
Project-URL: repository, https://github.com/atav928/aquasec-api
Project-URL: homepage, https://www.tavnets.com/blog/aquasec/
Keywords: aquasec,aqua security,workload protection
Classifier: Programming Language :: Python :: 3
Requires-Python: <4,>=3.8
License-File: LICENSE
Requires-Dist: requests (>=2.26.0)
Requires-Dist: PyJWT (~=2.6.0)
Requires-Dist: dataclasses (>=0.6)
Requires-Dist: PyYAML (>=6.0)
Requires-Dist: dict-to-dataclass (~=0.0.8)
Requires-Dist: importlib-metadata ; python_version < "3.8"
